mcp_test3/__init__.py
mcp_test3/main.py
rgb_converter/__init__.py
rgb_converter/main.py
rgb_converter-0.1.0.dist-info/licenses/LICENSE
rgb_converter-0.1.0.dist-info/METADATA
rgb_converter-0.1.0.dist-info/WHEEL
rgb_converter-0.1.0.dist-info/top_level.txt
rgb_converter-0.1.0.dist-info/RECORD
