Metadata-Version: 2.4
Name: rgb-converter
Version: 0.1.0
Summary: RGB Color Converter - FastMCP Example
Author-email: Your Name <your.email@example.com>
License: MIT
Project-URL: Homepage, https://github.com/yourusername/mcp-test3
Project-URL: Bug Tracker, https://github.com/yourusername/mcp-test3/issues
Classifier: Programming Language :: Python :: 3
Classifier: License :: OSI Approved :: MIT License
Classifier: Operating System :: OS Independent
Requires-Python: >=3.13
License-File: LICENSE
Requires-Dist: mcp[cli]>=1.13.0
Requires-Dist: webcolors>=1.13
Dynamic: license-file
